README.txt
setup.py
Products/__init__.py
Products.InlinePhotoAlbum.egg-info/PKG-INFO
Products.InlinePhotoAlbum.egg-info/SOURCES.txt
Products.InlinePhotoAlbum.egg-info/dependency_links.txt
Products.InlinePhotoAlbum.egg-info/entry_points.txt
Products.InlinePhotoAlbum.egg-info/namespace_packages.txt
Products.InlinePhotoAlbum.egg-info/not-zip-safe
Products.InlinePhotoAlbum.egg-info/requires.txt
Products.InlinePhotoAlbum.egg-info/top_level.txt
Products/InlinePhotoAlbum/__init__.py
Products/InlinePhotoAlbum/configure.zcml
Products/InlinePhotoAlbum/tests.py
Products/InlinePhotoAlbum/version.txt
Products/InlinePhotoAlbum/browser/__init__.py
Products/InlinePhotoAlbum/browser/configure.zcml
Products/InlinePhotoAlbum/browser/images/lightbox-blank.gif
Products/InlinePhotoAlbum/browser/images/lightbox-btn-close.gif
Products/InlinePhotoAlbum/browser/images/lightbox-btn-next.gif
Products/InlinePhotoAlbum/browser/images/lightbox-btn-prev.gif
Products/InlinePhotoAlbum/browser/images/lightbox-ico-loading.gif
Products/InlinePhotoAlbum/browser/javascripts/inlinephotoalbum.js
Products/InlinePhotoAlbum/browser/javascripts/jquery.lightbox-0.5.min.js
Products/InlinePhotoAlbum/browser/stylesheets/inlinephotoalbum.css
Products/InlinePhotoAlbum/browser/stylesheets/jquery.lightbox-0.5.css
Products/InlinePhotoAlbum/browser/templates/photoalbum.pt
Products/InlinePhotoAlbum/browser/templates/photoalbum_bare.pt
Products/InlinePhotoAlbum/browser/views/__init__.py
Products/InlinePhotoAlbum/browser/views/photoalbum.py
Products/InlinePhotoAlbum/profiles/default/cssregistry.xml
Products/InlinePhotoAlbum/profiles/default/jsregistry.xml
Products/InlinePhotoAlbum/profiles/default/metadata.xml
docs/HISTORY.txt
docs/INSTALL.txt
docs/LICENSE.GPL
docs/LICENSE.txt
docs/TODO.txt