Metadata-Version: 1.0
Name: Products.InlinePhotoAlbum
Version: 1.3rc2
Summary: Display an image gallery inside a Plone rich text area
Home-page: http://plone.org/products/InlinePhotoAlbum
Author: Huub Bouma
Author-email: info@gw20e.com
License: GPL
Keywords: plone gallery inline embed
Platform: UNKNOWN
Classifier: Framework :: Plone
Classifier: Programming Language :: Python
